marshmallowjson/__init__.py
marshmallowjson/cli.py
marshmallowjson/exceptions.py
marshmallowjson/marshmallowjson.py
marshmallowjson-0.4.5.dist-info/METADATA
marshmallowjson-0.4.5.dist-info/RECORD
marshmallowjson-0.4.5.dist-info/WHEEL
marshmallowjson-0.4.5.dist-info/entry_points.txt
marshmallowjson-0.4.5.dist-info/top_level.txt
