Metadata-Version: 2.1
Name: marshmallowjson
Version: 0.4.5
Summary: Turns a JSON type definition into a marshmallow validation and serialization toolkit.
Home-page: https://github.com/tech-teach/marshmallowjson
Author: Oscar David Arbeláez
Author-email: odarbelaeze@gmail.com
License: MIT license
Keywords: marshmallowjson
Platform: UNKNOWN
Classifier: Development Status :: 2 - Pre-Alpha
Classifier: Intended Audience :: Developers
Classifier: License :: OSI Approved :: MIT License
Classifier: Natural Language :: English
Classifier: Programming Language :: Python :: 3
Classifier: Programming Language :: Python :: 3.5
Classifier: Programming Language :: Python :: 3.6
Requires-Dist: Click (>=6.0)
Requires-Dist: marshmallow (<3.0,>=2.15.0)
